{
    "palette": {
        "dark": {
            "--semi-black": "0,0,0",
            "--semi-red-0": "108,11,9",
            "--semi-red-1": "144,23,16",
            "--semi-red-2": "180,39,25",
            "--semi-red-3": "215,59,36",
            "--semi-red-4": "251,82,50",
            "--semi-red-5": "252,122,90",
            "--semi-red-6": "253,159,131",
            "--semi-red-7": "253,193,172",
            "--semi-red-8": "254,225,213",
            "--semi-red-9": "255,244,239",
            "--semi-white": "255,255,255",
            "--semi-blue-0": "5,47,112",
            "--semi-blue-1": "10,68,148",
            "--semi-blue-2": "19,90,184",
            "--semi-blue-3": "29,114,219",
            "--semi-blue-4": "41,141,255",
            "--semi-blue-5": "84,166,255",
            "--semi-blue-6": "127,191,255",
            "--semi-blue-7": "169,213,255",
            "--semi-blue-8": "212,235,255",
            "--semi-blue-9": "239,248,255",
            "--semi-cyan-0": "4,51,61",
            "--semi-cyan-1": "7,78,92",
            "--semi-cyan-2": "10,105,123",
            "--semi-cyan-3": "14,134,153",
            "--semi-cyan-4": "19,164,184",
            "--semi-cyan-5": "56,184,198",
            "--semi-cyan-6": "98,203,212",
            "--semi-cyan-7": "145,221,227",
            "--semi-cyan-8": "198,239,241",
            "--semi-cyan-9": "231,247,248",
            "--semi-grey-0": "39,39,34",
            "--semi-grey-1": "59,58,52",
            "--semi-grey-2": "78,77,70",
            "--semi-grey-3": "98,97,88",
            "--semi-grey-4": "117,116,107",
            "--semi-grey-5": "146,146,136",
            "--semi-grey-6": "176,175,167",
            "--semi-grey-7": "205,205,198",
            "--semi-grey-8": "234,234,230",
            "--semi-grey-9": "249,249,249",
            "--semi-lime-0": "46,70,3",
            "--semi-lime-1": "71,105,5",
            "--semi-lime-2": "97,141,9",
            "--semi-lime-3": "125,176,12",
            "--semi-lime-4": "154,211,17",
            "--semi-lime-5": "167,220,58",
            "--semi-lime-6": "183,229,102",
            "--semi-lime-7": "203,237,150",
            "--semi-lime-8": "227,246,201",
            "--semi-lime-9": "243,251,233",
            "--semi-pink-0": "92,7,42",
            "--semi-pink-1": "128,14,56",
            "--semi-pink-2": "164,23,70",
            "--semi-pink-3": "199,34,84",
            "--semi-pink-4": "235,47,98",
            "--semi-pink-5": "239,86,122",
            "--semi-pink-6": "243,126,150",
            "--semi-pink-7": "247,168,182",
            "--semi-pink-8": "251,211,216",
            "--semi-pink-9": "253,238,240",
            "--semi-teal-0": "2,58,60",
            "--semi-teal-1": "4,88,90",
            "--semi-teal-2": "7,119,119",
            "--semi-teal-3": "10,149,147",
            "--semi-teal-4": "14,179,174",
            "--semi-teal-5": "51,194,187",
            "--semi-teal-6": "94,209,202",
            "--semi-teal-7": "142,225,218",
            "--semi-teal-8": "196,240,236",
            "--semi-teal-9": "230,247,246",
            "--semi-amber-0": "81,50,9",
            "--semi-amber-1": "121,81,15",
            "--semi-amber-2": "161,115,22",
            "--semi-amber-3": "202,153,30",
            "--semi-amber-4": "242,195,38",
            "--semi-amber-5": "245,212,80",
            "--semi-amber-6": "247,227,122",
            "--semi-amber-7": "250,239,166",
            "--semi-amber-8": "252,248,210",
            "--semi-amber-9": "254,252,237",
            "--semi-green-0": "18,60,27",
            "--semi-green-1": "28,90,41",
            "--semi-green-2": "39,119,54",
            "--semi-green-3": "50,149,67",
            "--semi-green-4": "62,179,80",
            "--semi-green-5": "93,194,106",
            "--semi-green-6": "127,209,137",
            "--semi-green-7": "166,225,172",
            "--semi-green-8": "208,240,211",
            "--semi-green-9": "236,247,237",
            "--semi-indigo-0": "23,28,101",
            "--semi-indigo-1": "32,38,122",
            "--semi-indigo-2": "41,51,142",
            "--semi-indigo-3": "52,64,163",
            "--semi-indigo-4": "64,79,183",
            "--semi-indigo-5": "95,109,197",
            "--semi-indigo-6": "129,142,212",
            "--semi-indigo-7": "167,178,226",
            "--semi-indigo-8": "209,215,241",
            "--semi-indigo-9": "237,239,248",
            "--semi-orange-0": "85,34,3",
            "--semi-orange-1": "128,58,6",
            "--semi-orange-2": "170,86,10",
            "--semi-orange-3": "213,119,15",
            "--semi-orange-4": "255,156,20",
            "--semi-orange-5": "255,182,67",
            "--semi-orange-6": "255,205,114",
            "--semi-orange-7": "255,225,161",
            "--semi-orange-8": "255,241,208",
            "--semi-orange-9": "255,250,237",
            "--semi-purple-0": "78,16,97",
            "--semi-purple-1": "99,23,118",
            "--semi-purple-2": "120,31,138",
            "--semi-purple-3": "143,40,159",
            "--semi-purple-4": "166,51,179",
            "--semi-purple-5": "187,83,194",
            "--semi-purple-6": "206,120,209",
            "--semi-purple-7": "225,160,225",
            "--semi-purple-8": "240,206,239",
            "--semi-purple-9": "247,235,247",
            "--semi-violet-0": "50,27,119",
            "--semi-violet-1": "65,36,140",
            "--semi-violet-2": "82,46,160",
            "--semi-violet-3": "100,57,181",
            "--semi-violet-4": "120,70,201",
            "--semi-violet-5": "147,101,212",
            "--semi-violet-6": "174,136,223",
            "--semi-violet-7": "202,173,233",
            "--semi-violet-8": "229,212,244",
            "--semi-violet-9": "244,238,250",
            "--semi-yellow-0": "84,74,3",
            "--semi-yellow-1": "126,109,6",
            "--semi-yellow-2": "168,144,10",
            "--semi-yellow-3": "210,176,15",
            "--semi-yellow-4": "252,208,20",
            "--semi-yellow-5": "253,224,67",
            "--semi-yellow-6": "253,236,113",
            "--semi-yellow-7": "254,246,160",
            "--semi-yellow-8": "254,252,208",
            "--semi-yellow-9": "255,254,236",
            "--semi-light-blue-0": "0,52,97",
            "--semi-light-blue-1": "0,74,133",
            "--semi-light-blue-2": "3,98,169",
            "--semi-light-blue-3": "10,124,204",
            "--semi-light-blue-4": "19,153,240",
            "--semi-light-blue-5": "64,175,243",
            "--semi-light-blue-6": "110,197,246",
            "--semi-light-blue-7": "157,217,249",
            "--semi-light-blue-8": "206,237,252",
            "--semi-light-blue-9": "235,248,254",
            "--semi-light-green-0": "37,61,19",
            "--semi-light-green-1": "58,92,29",
            "--semi-light-green-2": "79,123,40",
            "--semi-light-green-3": "101,153,52",
            "--semi-light-green-4": "124,184,64",
            "--semi-light-green-5": "148,198,95",
            "--semi-light-green-6": "174,212,129",
            "--semi-light-green-7": "200,227,167",
            "--semi-light-green-8": "227,241,209",
            "--semi-light-green-9": "243,248,237"
        },
        "light": {
            "--semi-black": "0,0,0",
            "--semi-red-0": "254,243,237",
            "--semi-red-1": "254,223,210",
            "--semi-red-2": "253,188,165",
            "--semi-red-3": "252,150,120",
            "--semi-red-4": "251,110,76",
            "--semi-red-5": "249,68,32",
            "--semi-red-6": "214,46,21",
            "--semi-red-7": "178,28,12",
            "--semi-red-8": "142,14,5",
            "--semi-red-9": "107,4,1",
            "--semi-white": "255,255,255",
            "--semi-blue-0": "234,245,255",
            "--semi-blue-1": "203,230,254",
            "--semi-blue-2": "152,204,253",
            "--semi-blue-3": "101,176,252",
            "--semi-blue-4": "50,146,251",
            "--semi-blue-5": "0,115,251",
            "--semi-blue-6": "0,95,215",
            "--semi-blue-7": "0,76,179",
            "--semi-blue-8": "0,59,143",
            "--semi-blue-9": "0,42,108",
            "--semi-cyan-0": "229,247,248",
            "--semi-cyan-1": "194,238,240",
            "--semi-cyan-2": "138,220,226",
            "--semi-cyan-3": "88,200,211",
            "--semi-cyan-4": "44,181,197",
            "--semi-cyan-5": "5,161,182",
            "--semi-cyan-6": "3,131,152",
            "--semi-cyan-7": "1,103,122",
            "--semi-cyan-8": "0,75,91",
            "--semi-cyan-9": "0,49,61",
            "--semi-grey-0": "249,249,249",
            "--semi-grey-1": "234,234,230",
            "--semi-grey-2": "205,205,198",
            "--semi-grey-3": "176,175,167",
            "--semi-grey-4": "146,146,136",
            "--semi-grey-5": "117,116,107",
            "--semi-grey-6": "98,97,88",
            "--semi-grey-7": "78,77,70",
            "--semi-grey-8": "59,58,52",
            "--semi-grey-9": "39,39,34",
            "--semi-lime-0": "241,250,230",
            "--semi-lime-1": "224,246,197",
            "--semi-lime-2": "198,237,142",
            "--semi-lime-3": "177,228,91",
            "--semi-lime-4": "159,219,44",
            "--semi-lime-5": "145,209,0",
            "--semi-lime-6": "118,175,0",
            "--semi-lime-7": "92,140,0",
            "--semi-lime-8": "67,105,0",
            "--semi-lime-9": "44,70,0",
            "--semi-pink-0": "253,236,238",
            "--semi-pink-1": "251,207,212",
            "--semi-pink-2": "246,161,174",
            "--semi-pink-3": "242,116,139",
            "--semi-pink-4": "238,72,109",
            "--semi-pink-5": "233,30,82",
            "--semi-pink-6": "198,20,71",
            "--semi-pink-7": "162,11,60",
            "--semi-pink-8": "126,5,48",
            "--semi-pink-9": "91,1,36",
            "--semi-teal-0": "228,247,246",
            "--semi-teal-1": "192,240,236",
            "--semi-teal-2": "135,224,219",
            "--semi-teal-3": "84,209,203",
            "--semi-teal-4": "39,194,189",
            "--semi-teal-5": "0,179,176",
            "--semi-teal-6": "0,148,149",
            "--semi-teal-7": "0,116,119",
            "--semi-teal-8": "0,86,89",
            "--semi-teal-9": "0,56,60",
            "--semi-amber-0": "254,252,235",
            "--semi-amber-1": "252,248,206",
            "--semi-amber-2": "249,238,158",
            "--semi-amber-3": "246,225,111",
            "--semi-amber-4": "243,209,65",
            "--semi-amber-5": "240,191,20",
            "--semi-amber-6": "200,150,15",
            "--semi-amber-7": "160,112,10",
            "--semi-amber-8": "120,78,6",
            "--semi-amber-9": "80,48,3",
            "--semi-green-0": "236,247,237",
            "--semi-green-1": "208,240,211",
            "--semi-green-2": "164,224,171",
            "--semi-green-3": "125,209,136",
            "--semi-green-4": "90,194,105",
            "--semi-green-5": "59,179,78",
            "--semi-green-6": "48,149,65",
            "--semi-green-7": "37,119,53",
            "--semi-green-8": "27,89,40",
            "--semi-green-9": "17,60,27",
            "--semi-indigo-0": "236,239,248",
            "--semi-indigo-1": "209,215,240",
            "--semi-indigo-2": "167,177,226",
            "--semi-indigo-3": "128,141,211",
            "--semi-indigo-4": "94,108,196",
            "--semi-indigo-5": "63,77,181",
            "--semi-indigo-6": "51,62,161",
            "--semi-indigo-7": "40,49,141",
            "--semi-indigo-8": "31,37,120",
            "--semi-indigo-9": "23,27,100",
            "--semi-orange-0": "255,249,234",
            "--semi-orange-1": "255,240,204",
            "--semi-orange-2": "254,222,152",
            "--semi-orange-3": "254,200,101",
            "--semi-orange-4": "253,176,51",
            "--semi-orange-5": "253,148,0",
            "--semi-orange-6": "210,112,0",
            "--semi-orange-7": "168,82,0",
            "--semi-orange-8": "126,55,0",
            "--semi-orange-9": "84,32,0",
            "--semi-purple-0": "247,233,247",
            "--semi-purple-1": "240,202,238",
            "--semi-purple-2": "224,155,224",
            "--semi-purple-3": "207,111,209",
            "--semi-purple-4": "187,73,194",
            "--semi-purple-5": "166,40,179",
            "--semi-purple-6": "142,30,158",
            "--semi-purple-7": "119,22,138",
            "--semi-purple-8": "98,15,117",
            "--semi-purple-9": "77,10,97",
            "--semi-violet-0": "244,237,249",
            "--semi-violet-1": "227,209,244",
            "--semi-violet-2": "199,167,233",
            "--semi-violet-3": "171,127,222",
            "--semi-violet-4": "142,91,211",
            "--semi-violet-5": "114,58,199",
            "--semi-violet-6": "94,47,179",
            "--semi-violet-7": "76,37,159",
            "--semi-violet-8": "60,28,138",
            "--semi-violet-9": "45,20,118",
            "--semi-yellow-0": "254,255,234",
            "--semi-yellow-1": "253,254,203",
            "--semi-yellow-2": "253,253,152",
            "--semi-yellow-3": "253,247,101",
            "--semi-yellow-4": "252,238,50",
            "--semi-yellow-5": "251,225,0",
            "--semi-yellow-6": "209,191,0",
            "--semi-yellow-7": "167,156,0",
            "--semi-yellow-8": "126,119,0",
            "--semi-yellow-9": "84,81,0",
            "--semi-light-blue-0": "233,247,253",
            "--semi-light-blue-1": "201,235,252",
            "--semi-light-blue-2": "149,213,248",
            "--semi-light-blue-3": "98,191,245",
            "--semi-light-blue-4": "48,167,242",
            "--semi-light-blue-5": "0,142,238",
            "--semi-light-blue-6": "0,118,203",
            "--semi-light-blue-7": "0,94,167",
            "--semi-light-blue-8": "0,72,131",
            "--semi-light-blue-9": "0,51,96",
            "--semi-light-green-0": "243,248,236",
            "--semi-light-green-1": "226,240,208",
            "--semi-light-green-2": "198,226,165",
            "--semi-light-green-3": "171,211,126",
            "--semi-light-green-4": "145,197,91",
            "--semi-light-green-5": "120,182,60",
            "--semi-light-green-6": "98,152,49",
            "--semi-light-green-7": "76,122,38",
            "--semi-light-green-8": "56,91,27",
            "--semi-light-green-9": "36,61,18"
        }
    },
    "tokens": {
        "color": {
            "dark": {
                "bg/--semi-color-bg-0": "rgb(22,22,26)",
                "bg/--semi-color-bg-1": "rgb(35,36,41)",
                "bg/--semi-color-bg-2": "rgb(53,54,60)",
                "bg/--semi-color-bg-3": "rgb(67,68,74)",
                "bg/--semi-color-bg-4": "rgb(79,81,89)",
                "link/--semi-color-link": "var(--semi-color-primary)",
                "nav/--semi-color-nav-bg": "var(--semi-color-bg-1)",
                "black/--semi-color-black": "rgba(var(--semi-black),1)",
                "fill/--semi-color-fill-0": "rgba(var(--semi-grey-8),0.05)",
                "fill/--semi-color-fill-1": "rgba(var(--semi-grey-8),0.09)",
                "fill/--semi-color-fill-2": "rgba(var(--semi-grey-8),0.13)",
                "text/--semi-color-text-0": "rgba(var(--semi-grey-9),1)",
                "text/--semi-color-text-1": "rgba(var(--semi-grey-9),0.8)",
                "text/--semi-color-text-2": "rgba(var(--semi-grey-9),0.6)",
                "text/--semi-color-text-3": "rgba(var(--semi-grey-9),0.35)",
                "white/--semi-color-white": "#E4E7F5",
                "bg/--semi-color-overlay-bg": "rgba(22, 22, 26, 0.6)",
                "border/--semi-color-border": "rgba(var(--semi-grey-1),1)",
                "danger/--semi-color-danger": "rgba(var(--semi-red-5),1)",
                "shadow/--semi-color-shadow": "rgba(0,0,0,.04)",
                "border/--semi-color-border-1": "rgba(var(--semi-grey-2),1)",
                "border/--semi-color-border-2": "rgba(var(--semi-grey-3),1)",
                "border/--semi-color-border-3": "rgba(var(--semi-grey-5),1)",
                "default/--semi-color-default": "rgba(var(--semi-grey-0),1)",
                "link/--semi-color-link-hover": "var(--semi-color-primary-hover)",
                "primary/--semi-color-primary": "rgba(var(--semi-yellow-5),1)",
                "success/--semi-color-success": "rgba(var(--semi-green-5),1)",
                "warning/--semi-color-warning": "rgba(var(--semi-orange-5),1)",
                "link/--semi-color-link-active": "var(--semi-color-primary-active)",
                "link/--semi-color-link-visited": "var(--semi-color-primary)",
                "tertiary/--semi-color-tertiary": "rgba(var(--semi-grey-5),1)",
                "danger/--semi-color-danger-hover": "rgba(var(--semi-red-6),1)",
                "secondary/--semi-color-secondary": "rgba(var(--semi-yellow-5),1)",
                "danger/--semi-color-danger-active": "rgba(var(--semi-red-7),1)",
                "disabled/--semi-color-disabled-bg": "rgba(var(--semi-grey-2),1)",
                "default/--semi-color-default-hover": "rgba(var(--semi-grey-1),1)",
                "primary/--semi-color-primary-hover": "rgba(var(--semi-yellow-6),1)",
                "success/--semi-color-success-hover": "rgba(var(--semi-green-6),1)",
                "warning/--semi-color-warning-hover": "rgba(var(--semi-orange-6),1)",
                "default/--semi-color-default-active": "rgba(var(--semi-grey-2),1)",
                "disabled/--semi-color-disabled-fill": "rgba(var(--semi-grey-8),0.04)",
                "disabled/--semi-color-disabled-text": "rgba(var(--semi-grey-9),0.35)",
                "primary/--semi-color-primary-active": "rgba(var(--semi-yellow-7),1)",
                "success/--semi-color-success-active": "rgba(var(--semi-green-7),1)",
                "warning/--semi-color-warning-active": "rgba(var(--semi-orange-7),1)",
                "tertiary/--semi-color-tertiary-hover": "rgba(var(--semi-grey-6),1)",
                "disabled/--semi-color-disabled-border": "rgba(var(--semi-grey-9),0.04)",
                "primary/--semi-color-primary-disabled": "rgba(var(--semi-yellow-2),1)",
                "success/--semi-color-success-disabled": "rgba(var(--semi-green-2),1)",
                "tertiary/--semi-color-tertiary-active": "rgba(var(--semi-grey-7),1)",
                "secondary/--semi-color-secondary-hover": "rgba(var(--semi-yellow-6),1)",
                "secondary/--semi-color-secondary-active": "rgba(var(--semi-yellow-7),1)",
                "secondary/--semi-color-secondary-disabled": "rgba(var(--semi-yellow-2),1)",
                "danger-light/--semi-color-danger-light-focus": "rgba(var(--semi-red-6),0.65)",
                "danger-light/--semi-color-danger-light-hover": "rgba(var(--semi-red-6),0.35)",
                "danger-light/--semi-color-danger-light-active": "rgba(var(--semi-red-6),0.5)",
                "danger-light/--semi-color-danger-light-default": "rgba(var(--semi-red-6),0.2)",
                "primary-light/--semi-color-primary-light-hover": "rgba(var(--semi-yellow-1),1)",
                "success-light/--semi-color-success-light-hover": "rgba(var(--semi-green-1),1)",
                "warning-light/--semi-color-warning-light-focus": "rgba(var(--semi-orange-6),0.65)",
                "warning-light/--semi-color-warning-light-hover": "rgba(var(--semi-orange-6),0.35)",
                "primary-light/--semi-color-primary-light-active": "rgba(var(--semi-yellow-2),1)",
                "success-light/--semi-color-success-light-active": "rgba(var(--semi-green-2),1)",
                "warning-light/--semi-color-warning-light-active": "rgba(var(--semi-orange-6),5)",
                "primary-light/--semi-color-primary-light-default": "rgba(var(--semi-yellow-0),1)",
                "success-light/--semi-color-success-light-default": "rgba(var(--semi-green-0),1)",
                "tertiary-light/--semi-color-tertiary-light-hover": "rgba(var(--semi-grey-1),1)",
                "warning-light/--semi-color-warning-light-default": "rgba(var(--semi-orange-6),0.2)",
                "tertiary-light/--semi-color-tertiary-light-active": "rgba(var(--semi-grey-2),1)",
                "secondary-light/--semi-color-secondary-light-hover": "rgba(var(--semi-yellow-1),1)",
                "tertiary-light/--semi-color-tertiary-light-default": "rgba(var(--semi-grey-0),1)",
                "secondary-light/--semi-color-secondary-light-active": "rgba(var(--semi-yellow-2),1)",
                "secondary-light/--semi-color-secondary-light-default": "rgba(var(--semi-yellow-0),1)"
            },
            "light": {
                "bg/--semi-color-bg-0": "var(--semi-color-white)",
                "bg/--semi-color-bg-1": "var(--semi-color-white)",
                "bg/--semi-color-bg-2": "var(--semi-color-white)",
                "bg/--semi-color-bg-3": "var(--semi-color-white)",
                "bg/--semi-color-bg-4": "var(--semi-color-white)",
                "info/--semi-color-info": "rgba(0,100,250, 1)",
                "link/--semi-color-link": "rgba(var(--semi-yellow-5),1)",
                "nav/--semi-color-nav-bg": "var(--semi-color-bg-1)",
                "black/--semi-color-black": "rgba(var(--semi-black),1)",
                "fill/--semi-color-fill-0": "rgba(var(--semi-grey-8),0.05)",
                "fill/--semi-color-fill-1": "rgba(var(--semi-grey-8),0.09)",
                "fill/--semi-color-fill-2": "rgba(var(--semi-grey-8),0.13)",
                "text/--semi-color-text-0": "rgba(var(--semi-grey-9),1)",
                "text/--semi-color-text-1": "rgba(var(--semi-grey-9),0.8)",
                "text/--semi-color-text-2": "rgba(var(--semi-grey-9),0.6)",
                "text/--semi-color-text-3": "rgba(var(--semi-grey-9),0.35)",
                "white/--semi-color-white": "rgba(var(--semi-white),1)",
                "bg/--semi-color-overlay-bg": "rgba(22, 22, 26, 0.6)",
                "border/--semi-color-border": "rgba(var(--semi-grey-1),1)",
                "danger/--semi-color-danger": "rgba(var(--semi-red-5),1)",
                "shadow/--semi-color-shadow": "rgba(0,0,0,.04)",
                "border/--semi-color-border-1": "rgba(var(--semi-grey-2),1)",
                "border/--semi-color-border-2": "rgba(var(--semi-grey-3),1)",
                "border/--semi-color-border-3": "rgba(var(--semi-grey-5),1)",
                "default/--semi-color-default": "rgba(var(--semi-grey-0),1)",
                "info/--semi-color-info-hover": "rgba(0,82,214, 1)",
                "link/--semi-color-link-hover": "rgba(var(--semi-yellow-6),1)",
                "primary/--semi-color-primary": "rgba(var(--semi-yellow-5),1)",
                "success/--semi-color-success": "rgba(var(--semi-green-5),1)",
                "warning/--semi-color-warning": "rgba(var(--semi-orange-5),1)",
                "info/--semi-color-info-active": "rgba(0,65,179, 1)",
                "link/--semi-color-link-active": "rgba(var(--semi-yellow-7),1)",
                "link/--semi-color-link-visited": "rgba(var(--semi-yellow-5),1)",
                "tertiary/--semi-color-tertiary": "rgba(var(--semi-grey-5),1)",
                "focus/--semi-color-focus-border": "rgba(var(--semi-yellow-5),1)",
                "info/--semi-color-info-disabled": "rgba(152,197,253, 1)",
                "danger/--semi-color-danger-hover": "rgba(var(--semi-red-6),1)",
                "secondary/--semi-color-secondary": "rgba(var(--semi-yellow-5),1)",
                "danger/--semi-color-danger-active": "rgba(var(--semi-red-7),1)",
                "disabled/--semi-color-disabled-bg": "rgba(var(--semi-grey-2),1)",
                "default/--semi-color-default-hover": "rgba(var(--semi-grey-1),1)",
                "primary/--semi-color-primary-hover": "rgba(var(--semi-yellow-6),1)",
                "success/--semi-color-success-hover": "rgba(var(--semi-green-6),1)",
                "warning/--semi-color-warning-hover": "rgba(var(--semi-orange-6),1)",
                "default/--semi-color-default-active": "rgba(var(--semi-grey-2),1)",
                "disabled/--semi-color-disabled-fill": "rgba(var(--semi-grey-8),0.04)",
                "disabled/--semi-color-disabled-text": "rgba(var(--semi-grey-9),0.35)",
                "primary/--semi-color-primary-active": "rgba(var(--semi-yellow-7),1)",
                "success/--semi-color-success-active": "rgba(var(--semi-green-7),1)",
                "warning/--semi-color-warning-active": "rgba(var(--semi-orange-7),1)",
                "tertiary/--semi-color-tertiary-hover": "rgba(var(--semi-grey-6),1)",
                "disabled/--semi-color-disabled-border": "rgba(var(--semi-grey-9),0.04)",
                "primary/--semi-color-primary-disabled": "rgba(var(--semi-yellow-2),1)",
                "success/--semi-color-success-disabled": "rgba(var(--semi-green-2),1)",
                "tertiary/--semi-color-tertiary-active": "rgba(var(--semi-grey-7),1)",
                "secondary/--semi-color-secondary-hover": "rgba(var(--semi-yellow-6),1)",
                "secondary/--semi-color-secondary-active": "rgba(var(--semi-yellow-7),1)",
                "info-light/--semi-color-info-light-hover": "rgba(203,227,254, 1)",
                "primary/--semi-color-primary-light-hover": "rgba(var(--semi-yellow-1),1)",
                "info-light/--semi-color-info-light-active": "rgba(152,197,253, 1)",
                "primary/--semi-color-primary-light-active": "rgba(var(--semi-yellow-2),1)",
                "secondary/--semi-color-secondary-disabled": "rgba(var(--semi-yellow-2),1)",
                "info-light/--semi-color-info-light-default": "rgba(234,244,255, 1)",
                "primary/--semi-color-primary-light-default": "rgba(var(--semi-yellow-0),1)",
                "danger-light/--semi-color-danger-light-hover": "rgba(var(--semi-red-1),1)",
                "danger-light/--semi-color-danger-light-active": "rgba(var(--semi-red-2),1)",
                "danger-light/--semi-color-danger-light-default": "rgba(var(--semi-red-0),1)",
                "primary-light/--semi-color-primary-light-hover": "rgba(var(--semi-yellow-1),1)",
                "success-light/--semi-color-success-light-hover": "rgba(var(--semi-green-1),1)",
                "warning-light/--semi-color-warning-light-hover": "rgba(var(--semi-orange-1),1)",
                "primary-light/--semi-color-primary-light-active": "rgba(var(--semi-yellow-2),1)",
                "success-light/--semi-color-success-light-active": "rgba(var(--semi-green-2),1)",
                "warning-light/--semi-color-warning-light-active": "rgba(var(--semi-orange-3),1)",
                "primary-light/--semi-color-primary-light-default": "rgba(var(--semi-yellow-0),1)",
                "success-light/--semi-color-success-light-default": "rgba(var(--semi-green-0),1)",
                "tertiary-light/--semi-color-tertiary-light-hover": "rgba(var(--semi-grey-1),1)",
                "warning-light/--semi-color-warning-light-default": "rgba(var(--semi-orange-0),1)",
                "tertiary-light/--semi-color-tertiary-light-active": "rgba(var(--semi-grey-2),1)",
                "secondary-light/--semi-color-secondary-light-hover": "rgba(var(--semi-yellow-1),1)",
                "tertiary-light/--semi-color-tertiary-light-default": "rgba(var(--semi-grey-0),1)",
                "secondary-light/--semi-color-secondary-light-active": "rgba(var(--semi-yellow-2),1)",
                "secondary-light/--semi-color-secondary-light-default": "rgba(var(--semi-yellow-0),1)"
            }
        },
        "extra": {
            "shadow": {},
            "typography": {
                "small": {
                    "calcWay": "scaled",
                    "fontSizeDisable": true,
                    "selectedFontSize": 12,
                    "fontFamilyDisable": true,
                    "lineHeightDisable": true,
                    "userInputFontSize": 12,
                    "userInputFontFamily": [
                        "-apple-system",
                        "BlinkMacSystemFont",
                        "'Segoe UI'",
                        "'PingFang SC'",
                        "'Hiragino Sans GB'",
                        "'Microsoft YaHei'",
                        "'Helvetica Neue'",
                        "Helvetica",
                        "Arial",
                        "sans-serif"
                    ],
                    "userInputLineHeight": 16,
                    "letterSpacingDisable": true,
                    "userInputLetterSpacing": 0,
                    "userInputShiftFontSize": 0
                },
                "regular": {
                    "calcWay": "scaled",
                    "fontSizeDisable": true,
                    "selectedFontSize": 14,
                    "fontFamilyDisable": true,
                    "lineHeightDisable": true,
                    "userInputFontSize": 14,
                    "userInputFontFamily": [
                        "-apple-system",
                        "BlinkMacSystemFont",
                        "'Segoe UI'",
                        "'PingFang SC'",
                        "'Hiragino Sans GB'",
                        "'Microsoft YaHei'",
                        "'Helvetica Neue'",
                        "Helvetica",
                        "Arial",
                        "sans-serif"
                    ],
                    "userInputLineHeight": 20,
                    "letterSpacingDisable": true,
                    "userInputLetterSpacing": 0,
                    "userInputShiftFontSize": 0
                },
                "header-1": {
                    "calcWay": "scaled",
                    "fontSizeDisable": true,
                    "selectedFontSize": 32,
                    "fontFamilyDisable": true,
                    "lineHeightDisable": true,
                    "userInputFontSize": 32,
                    "userInputFontFamily": [
                        "-apple-system",
                        "BlinkMacSystemFont",
                        "'Segoe UI'",
                        "'PingFang SC'",
                        "'Hiragino Sans GB'",
                        "'Microsoft YaHei'",
                        "'Helvetica Neue'",
                        "Helvetica",
                        "Arial",
                        "sans-serif"
                    ],
                    "userInputLineHeight": 44,
                    "letterSpacingDisable": true,
                    "userInputLetterSpacing": 0,
                    "userInputShiftFontSize": 0
                },
                "header-2": {
                    "calcWay": "scaled",
                    "fontSizeDisable": true,
                    "selectedFontSize": 28,
                    "fontFamilyDisable": true,
                    "lineHeightDisable": true,
                    "userInputFontSize": 28,
                    "userInputFontFamily": [
                        "-apple-system",
                        "BlinkMacSystemFont",
                        "'Segoe UI'",
                        "'PingFang SC'",
                        "'Hiragino Sans GB'",
                        "'Microsoft YaHei'",
                        "'Helvetica Neue'",
                        "Helvetica",
                        "Arial",
                        "sans-serif"
                    ],
                    "userInputLineHeight": 40,
                    "letterSpacingDisable": true,
                    "userInputLetterSpacing": 0,
                    "userInputShiftFontSize": 0
                },
                "header-3": {
                    "calcWay": "scaled",
                    "fontSizeDisable": true,
                    "selectedFontSize": 24,
                    "fontFamilyDisable": true,
                    "lineHeightDisable": true,
                    "userInputFontSize": 24,
                    "userInputFontFamily": [
                        "-apple-system",
                        "BlinkMacSystemFont",
                        "'Segoe UI'",
                        "'PingFang SC'",
                        "'Hiragino Sans GB'",
                        "'Microsoft YaHei'",
                        "'Helvetica Neue'",
                        "Helvetica",
                        "Arial",
                        "sans-serif"
                    ],
                    "userInputLineHeight": 32,
                    "letterSpacingDisable": true,
                    "userInputLetterSpacing": 0,
                    "userInputShiftFontSize": 0
                },
                "header-4": {
                    "calcWay": "scaled",
                    "fontSizeDisable": true,
                    "selectedFontSize": 20,
                    "fontFamilyDisable": true,
                    "lineHeightDisable": true,
                    "userInputFontSize": 20,
                    "userInputFontFamily": [
                        "-apple-system",
                        "BlinkMacSystemFont",
                        "'Segoe UI'",
                        "'PingFang SC'",
                        "'Hiragino Sans GB'",
                        "'Microsoft YaHei'",
                        "'Helvetica Neue'",
                        "Helvetica",
                        "Arial",
                        "sans-serif"
                    ],
                    "userInputLineHeight": 28,
                    "letterSpacingDisable": true,
                    "userInputLetterSpacing": 0,
                    "userInputShiftFontSize": 0
                },
                "header-5": {
                    "calcWay": "scaled",
                    "fontSizeDisable": true,
                    "selectedFontSize": 18,
                    "fontFamilyDisable": true,
                    "lineHeightDisable": true,
                    "userInputFontSize": 18,
                    "userInputFontFamily": [
                        "-apple-system",
                        "BlinkMacSystemFont",
                        "'Segoe UI'",
                        "'PingFang SC'",
                        "'Hiragino Sans GB'",
                        "'Microsoft YaHei'",
                        "'Helvetica Neue'",
                        "Helvetica",
                        "Arial",
                        "sans-serif"
                    ],
                    "userInputLineHeight": 24,
                    "letterSpacingDisable": true,
                    "userInputLetterSpacing": 0,
                    "userInputShiftFontSize": 0
                },
                "header-6": {
                    "calcWay": "scaled",
                    "fontSizeDisable": true,
                    "selectedFontSize": 16,
                    "fontFamilyDisable": true,
                    "lineHeightDisable": true,
                    "userInputFontSize": 16,
                    "userInputFontFamily": [
                        "-apple-system",
                        "BlinkMacSystemFont",
                        "'Segoe UI'",
                        "'PingFang SC'",
                        "'Hiragino Sans GB'",
                        "'Microsoft YaHei'",
                        "'Helvetica Neue'",
                        "Helvetica",
                        "Arial",
                        "sans-serif"
                    ],
                    "userInputLineHeight": 22,
                    "letterSpacingDisable": true,
                    "userInputLetterSpacing": 0,
                    "userInputShiftFontSize": 0
                }
            }
        },
        "border": {
            "border-default": "1px solid var(--semi-color-border)"
        },
        "shadow": {
            "shadow-0": "none",
            "shadow-1": "none",
            "shadow-2": "0px 2px 4px rgba(0,0,0,0.14),0px 0px 1px rgba(0,0,0,0.16)",
            "shadow-knob": "0 4px 6px rgba(0,0,0,0.1),0 0 1px rgba(0,0,0,0.3)",
            "shadow-elevated": "0px 0px 1px rgba(0,0,0,0.3),0px 4px 14px rgba(0,0,0,0.1)"
        },
        "spacing": {},
        "components": {
            "modal": {
                "spacing": {
                    "$spacing-modal_content_withicon-marginLeft": "0"
                }
            },
            "button": {
                "color": {
                    "$color-button_primary-text-default": "black"
                }
            }
        },
        "typography": {
            "Header": {
                "header-1": {
                    "fontSize": "32px",
                    "fontFamily": "-apple-system, BlinkMacSystemFont, 'Segoe UI', 'PingFang SC', 'Hiragino Sans GB', 'Microsoft YaHei', 'Helvetica Neue', Helvetica, Arial, sans-serif",
                    "lineHeight": "44px",
                    "letterSpacing": "0px"
                },
                "header-2": {
                    "fontSize": "28px",
                    "fontFamily": "-apple-system, BlinkMacSystemFont, 'Segoe UI', 'PingFang SC', 'Hiragino Sans GB', 'Microsoft YaHei', 'Helvetica Neue', Helvetica, Arial, sans-serif",
                    "lineHeight": "40px",
                    "letterSpacing": "0px"
                },
                "header-3": {
                    "fontSize": "24px",
                    "fontFamily": "-apple-system, BlinkMacSystemFont, 'Segoe UI', 'PingFang SC', 'Hiragino Sans GB', 'Microsoft YaHei', 'Helvetica Neue', Helvetica, Arial, sans-serif",
                    "lineHeight": "32px",
                    "letterSpacing": "0px"
                },
                "header-4": {
                    "fontSize": "20px",
                    "fontFamily": "-apple-system, BlinkMacSystemFont, 'Segoe UI', 'PingFang SC', 'Hiragino Sans GB', 'Microsoft YaHei', 'Helvetica Neue', Helvetica, Arial, sans-serif",
                    "lineHeight": "28px",
                    "letterSpacing": "0px"
                },
                "header-5": {
                    "fontSize": "18px",
                    "fontFamily": "-apple-system, BlinkMacSystemFont, 'Segoe UI', 'PingFang SC', 'Hiragino Sans GB', 'Microsoft YaHei', 'Helvetica Neue', Helvetica, Arial, sans-serif",
                    "lineHeight": "24px",
                    "letterSpacing": "0px"
                },
                "header-6": {
                    "fontSize": "16px",
                    "fontFamily": "-apple-system, BlinkMacSystemFont, 'Segoe UI', 'PingFang SC', 'Hiragino Sans GB', 'Microsoft YaHei', 'Helvetica Neue', Helvetica, Arial, sans-serif",
                    "lineHeight": "22px",
                    "letterSpacing": "0px"
                }
            },
            "Paragraph": {
                "small": {
                    "fontSize": "12px",
                    "fontFamily": "-apple-system, BlinkMacSystemFont, 'Segoe UI', 'PingFang SC', 'Hiragino Sans GB', 'Microsoft YaHei', 'Helvetica Neue', Helvetica, Arial, sans-serif",
                    "lineHeight": "16px",
                    "letterSpacing": "0px"
                },
                "regular": {
                    "fontSize": "14px",
                    "fontFamily": "-apple-system, BlinkMacSystemFont, 'Segoe UI', 'PingFang SC', 'Hiragino Sans GB', 'Microsoft YaHei', 'Helvetica Neue', Helvetica, Arial, sans-serif",
                    "lineHeight": "20px",
                    "letterSpacing": "0px"
                }
            }
        },
        "presetColor": {
            "red": "#F93920",
            "blue": "#0077FA",
            "cyan": "#05A4B6",
            "grey": "#6b7075",
            "lime": "#9bd100",
            "pink": "#E91E63",
            "teal": "#00a696",
            "amber": "#F0B114",
            "green": "#38AA43",
            "indigo": "#3F51B5",
            "orange": "#fc8800",
            "purple": "#9C27B0",
            "violet": "#6A3AC7",
            "yellow": "#fac800",
            "light-blue": "#0095ee",
            "light-green": "#7bb63c"
        },
        "border-radius": {
            "--semi-border-radius-large": "12px",
            "--semi-border-radius-small": "12px",
            "--semi-border-radius-circle": "10000px",
            "--semi-border-radius-medium": "6px",
            "--semi-border-radius-extra-small": "3px"
        },
        "typography-base": {
            "scale": 1.25,
            "wordSpace": 0,
            "fontFamily": "-apple-system,BlinkMacSystemFont,'Segoe UI','PingFang SC','Hiragino Sans GB','Microsoft YaHei','Helvetica Neue',Helvetica,Arial,sans-serif",
            "letterSpace": 0,
            "baseFontSize": "16px",
            "lineHeightMultiplier": 1.1
        },
        "globalScssVariables": {}
    }
}