{
  "version": "1.2.0",
  "style": {
    "width": 620,
    "height": 820,
    "background": "",
    "classNames": []
  },
  "properties": {},
  "cssFiles": [],
  "jsFiles": [
    "composite:///js/guess.js"
  ],
  "elements": [
    {
      "title": "按钮",
      "path": "ridge-bootstrap/button",
      "id": "b7xkbe66u8",
      "style": {
        "position": "absolute",
        "visible": true,
        "x": 885,
        "y": 272,
        "width": 100,
        "height": 65
      },
      "styleEx": {},
      "props": {
        "text": "1",
        "type": "primary",
        "src": "",
        "size": "lg",
        "fontSize": 27,
        "style": "general",
        "rounded": false,
        "full": true,
        "disabled": false,
        "withBadge": false,
        "badgeCount": ""
      },
      "propEx": {},
      "events": {
        "onClick": [
          {
            "store": "NumberGuess",
            "method": "onBtnPress",
            "payload": "1"
          }
        ]
      },
      "visible": true,
      "locked": false,
      "full": false,
      "slots": []
    },
    {
      "title": "文本",
      "path": "ridge-bootstrap/typography",
      "id": "khw49z6y0a",
      "style": {
        "position": "absolute",
        "visible": true,
        "x": 0,
        "y": -2,
        "width": 213,
        "height": 67
      },
      "styleEx": {},
      "props": {
        "text": "2341",
        "color": "",
        "bgcolor": "",
        "fontSize": 64,
        "autoFontSize": false,
        "fontFamily": "",
        "ellipsis": false,
        "clamp": 1,
        "center": true,
        "effect": "",
        "classList": []
      },
      "propEx": {
        "text": "NumberGuess.state.input"
      },
      "events": {},
      "visible": true,
      "locked": false,
      "full": false,
      "slots": []
    },
    {
      "title": "按钮",
      "path": "ridge-bootstrap/button",
      "id": "bkojzzxq5i",
      "style": {
        "position": "absolute",
        "visible": true,
        "x": 683,
        "y": 157,
        "width": 100,
        "height": 65
      },
      "styleEx": {},
      "props": {
        "text": "2",
        "type": "primary",
        "src": "",
        "size": "lg",
        "fontSize": 27,
        "style": "general",
        "rounded": false,
        "full": true,
        "disabled": false,
        "withBadge": false,
        "badgeCount": ""
      },
      "propEx": {},
      "events": {
        "onClick": [
          {
            "store": "NumberGuess",
            "method": "onBtnPress",
            "payload": "2"
          }
        ]
      },
      "visible": true,
      "locked": false,
      "full": false,
      "slots": []
    },
    {
      "title": "按钮",
      "path": "ridge-bootstrap/button",
      "id": "7tdwyxmcgc",
      "style": {
        "position": "absolute",
        "visible": true,
        "x": 758,
        "y": 157,
        "width": 100,
        "height": 65
      },
      "styleEx": {},
      "props": {
        "text": "3",
        "type": "primary",
        "src": "",
        "size": "lg",
        "fontSize": 27,
        "style": "general",
        "rounded": false,
        "full": true,
        "disabled": false,
        "withBadge": false,
        "badgeCount": ""
      },
      "propEx": {},
      "events": {
        "onClick": [
          {
            "store": "NumberGuess",
            "method": "onBtnPress",
            "payload": "3"
          }
        ]
      },
      "visible": true,
      "locked": false,
      "full": false,
      "slots": []
    },
    {
      "title": "按钮",
      "path": "ridge-bootstrap/button",
      "id": "semhrj7nj1",
      "style": {
        "position": "absolute",
        "visible": true,
        "x": 885,
        "y": 356,
        "width": 100,
        "height": 65
      },
      "styleEx": {},
      "props": {
        "text": "4",
        "type": "primary",
        "src": "",
        "size": "lg",
        "fontSize": 27,
        "style": "general",
        "rounded": false,
        "full": true,
        "disabled": false,
        "withBadge": false,
        "badgeCount": ""
      },
      "propEx": {},
      "events": {
        "onClick": [
          {
            "store": "NumberGuess",
            "method": "onBtnPress",
            "payload": "4"
          }
        ]
      },
      "visible": true,
      "locked": false,
      "full": false,
      "slots": []
    },
    {
      "title": "按钮",
      "path": "ridge-bootstrap/button",
      "id": "yrsaghlwyo",
      "style": {
        "position": "absolute",
        "visible": true,
        "x": 976,
        "y": 356,
        "width": 100,
        "height": 65
      },
      "styleEx": {},
      "props": {
        "text": "5",
        "type": "primary",
        "src": "",
        "size": "lg",
        "fontSize": 27,
        "style": "general",
        "rounded": false,
        "full": true,
        "disabled": false,
        "withBadge": false,
        "badgeCount": ""
      },
      "propEx": {},
      "events": {
        "onClick": [
          {
            "store": "NumberGuess",
            "method": "onBtnPress",
            "payload": "5"
          }
        ]
      },
      "visible": true,
      "locked": false,
      "full": false,
      "slots": []
    },
    {
      "title": "按钮",
      "path": "ridge-bootstrap/button",
      "id": "cnuzivlho5",
      "style": {
        "position": "absolute",
        "visible": true,
        "x": 1067,
        "y": 356,
        "width": 100,
        "height": 65
      },
      "styleEx": {},
      "props": {
        "text": "6",
        "type": "primary",
        "src": "",
        "size": "lg",
        "fontSize": 27,
        "style": "general",
        "rounded": false,
        "full": true,
        "disabled": false,
        "withBadge": false,
        "badgeCount": ""
      },
      "propEx": {},
      "events": {
        "onClick": [
          {
            "store": "NumberGuess",
            "method": "onBtnPress",
            "payload": "6"
          }
        ]
      },
      "visible": true,
      "locked": false,
      "full": false,
      "slots": []
    },
    {
      "title": "按钮",
      "path": "ridge-bootstrap/button",
      "id": "5xwifz7wzt",
      "style": {
        "position": "absolute",
        "visible": true,
        "x": 891,
        "y": 447,
        "width": 100,
        "height": 65
      },
      "styleEx": {},
      "props": {
        "text": "7",
        "type": "primary",
        "src": "",
        "size": "lg",
        "fontSize": 27,
        "style": "general",
        "rounded": false,
        "full": true,
        "disabled": false,
        "withBadge": false,
        "badgeCount": ""
      },
      "propEx": {},
      "events": {
        "onClick": [
          {
            "store": "NumberGuess",
            "method": "onBtnPress",
            "payload": "7"
          }
        ]
      },
      "visible": true,
      "locked": false,
      "full": false,
      "slots": []
    },
    {
      "title": "按钮",
      "path": "ridge-bootstrap/button",
      "id": "erdhc14knm",
      "style": {
        "position": "absolute",
        "visible": true,
        "x": 976,
        "y": 447,
        "width": 100,
        "height": 65
      },
      "styleEx": {},
      "props": {
        "text": "8",
        "type": "primary",
        "src": "",
        "size": "lg",
        "fontSize": 27,
        "style": "general",
        "rounded": false,
        "full": true,
        "disabled": false,
        "withBadge": false,
        "badgeCount": ""
      },
      "propEx": {},
      "events": {
        "onClick": [
          {
            "store": "NumberGuess",
            "method": "onBtnPress",
            "payload": "8"
          }
        ]
      },
      "visible": true,
      "locked": false,
      "full": false,
      "slots": []
    },
    {
      "title": "按钮",
      "path": "ridge-bootstrap/button",
      "id": "swutric4ok",
      "style": {
        "position": "absolute",
        "visible": true,
        "x": 1067,
        "y": 447,
        "width": 100,
        "height": 65
      },
      "styleEx": {},
      "props": {
        "text": "9",
        "type": "primary",
        "src": "",
        "size": "lg",
        "fontSize": 27,
        "style": "general",
        "rounded": false,
        "full": true,
        "disabled": false,
        "withBadge": false,
        "badgeCount": ""
      },
      "propEx": {},
      "events": {
        "onClick": [
          {
            "store": "NumberGuess",
            "method": "onBtnPress",
            "payload": "9"
          }
        ]
      },
      "visible": true,
      "locked": false,
      "full": false,
      "slots": []
    },
    {
      "title": "按钮",
      "path": "ridge-bootstrap/button",
      "id": "ai55ywlu6o",
      "style": {
        "position": "absolute",
        "visible": true,
        "x": 885,
        "y": 472,
        "width": 100,
        "height": 65
      },
      "styleEx": {},
      "props": {
        "type": "danger",
        "src": "",
        "size": "lg",
        "fontSize": 27,
        "style": "general",
        "rounded": false,
        "full": true,
        "disabled": false,
        "withBadge": false,
        "badgeCount": "",
        "icon": "backspace"
      },
      "propEx": {},
      "events": {
        "onClick": [
          {
            "store": "NumberGuess",
            "method": "onBtnPress",
            "payload": "back"
          }
        ]
      },
      "visible": true,
      "locked": false,
      "full": false,
      "slots": []
    },
    {
      "title": "列表：反馈记录",
      "path": "ridge-container/list",
      "id": "we5srv7x4e",
      "style": {
        "position": "absolute",
        "visible": true,
        "x": 0,
        "y": 0,
        "width": 320,
        "height": 324,
        "alignSelfStretch": false,
        "flex": "12"
      },
      "styleEx": {},
      "props": {
        "dataSource": [],
        "selected": [],
        "children": [
          "yt1ysh6hd5"
        ],
        "overflowAuto": true,
        "direction": "y",
        "fixedHeight": true,
        "fixedWidth": false,
        "horizontalDivide": 1,
        "verticalDivide": 3,
        "sortable": false,
        "gap": 8,
        "classNames": []
      },
      "propEx": {
        "dataSource": "NumberGuess.state.attempts"
      },
      "events": {},
      "visible": true,
      "locked": false,
      "full": false,
      "slots": []
    },
    {
      "title": "模板：单项反馈",
      "path": "ridge-container/flex",
      "id": "yt1ysh6hd5",
      "style": {
        "position": "absolute",
        "visible": true,
        "x": 0,
        "y": 0,
        "width": 316,
        "height": 49
      },
      "styleEx": {},
      "props": {
        "direction": "row",
        "justify": "flex-start",
        "alignItems": "center",
        "flexWrap": false,
        "children": [
          "59qvsa963q",
          "ltsf0v59kj"
        ],
        "gap": 8,
        "padding": 2,
        "hoverable": false,
        "rectStyle": {},
        "classList": [
          "ridge-bootstrap/border-start",
          "ridge-bootstrap/ps-2",
          "ridge-bootstrap/border",
          "ridge-bootstrap/border-1",
          "ridge-bootstrap/border-body-tertiary",
          "ridge-bootstrap/rounded-2",
          "ridge-bootstrap/bg-body-tertiary"
        ]
      },
      "propEx": {},
      "events": {},
      "visible": true,
      "locked": false,
      "full": false,
      "slots": []
    },
    {
      "title": "correct",
      "path": "ridge-container/flex",
      "id": "hce3dn17tj",
      "style": {
        "position": "absolute",
        "visible": true,
        "x": 0,
        "y": 0,
        "width": 38,
        "height": 34
      },
      "styleEx": {},
      "props": {
        "direction": "row",
        "justify": "center",
        "alignItems": "center",
        "flexWrap": false,
        "children": [
          "awpi5pm8yk"
        ],
        "gap": 8,
        "padding": 8,
        "hoverable": false,
        "rectStyle": {},
        "classList": [
          "ridge-bootstrap/bg-success-subtle",
          "ridge-bootstrap/rounded-3",
          "ridge-bootstrap/shadow-sm"
        ]
      },
      "propEx": {},
      "events": {},
      "visible": true,
      "locked": false,
      "full": false,
      "slots": []
    },
    {
      "title": "列表：4个数字结果",
      "path": "ridge-container/list",
      "id": "ltsf0v59kj",
      "style": {
        "position": "absolute",
        "visible": true,
        "x": 0,
        "y": 0,
        "width": 171,
        "height": 37
      },
      "styleEx": {},
      "props": {
        "dataSource": [],
        "selected": [],
        "children": [
          "hn63go7hrq"
        ],
        "overflowAuto": false,
        "direction": "y",
        "fixedHeight": true,
        "fixedWidth": true,
        "horizontalDivide": 3,
        "verticalDivide": 3,
        "sortable": false,
        "gap": 4,
        "classNames": []
      },
      "propEx": {
        "dataSource": "NumberGuess.computed.oneTimeResult"
      },
      "events": {},
      "visible": true,
      "locked": false,
      "full": false,
      "slots": []
    },
    {
      "title": "切换容器",
      "path": "ridge-container/layers",
      "id": "hn63go7hrq",
      "style": {
        "position": "absolute",
        "visible": true,
        "x": 0,
        "y": 0,
        "width": 36,
        "height": 36
      },
      "styleEx": {},
      "props": {
        "current": "",
        "preload": true,
        "swipeable": false,
        "classList": [],
        "children": [
          "hce3dn17tj",
          "uvp1x413ns",
          "6ie68ja9mt"
        ]
      },
      "propEx": {
        "current": "NumberGuess.computed.oneTimeNumberType"
      },
      "events": {},
      "visible": true,
      "locked": false,
      "full": false,
      "slots": []
    },
    {
      "title": "数字",
      "path": "ridge-bootstrap/typography",
      "id": "awpi5pm8yk",
      "style": {
        "position": "absolute",
        "visible": true,
        "x": 0,
        "y": -23,
        "width": 20,
        "height": 21
      },
      "styleEx": {},
      "props": {
        "text": "2",
        "color": "",
        "bgcolor": "",
        "fontSize": 24,
        "autoFontSize": false,
        "fontFamily": "",
        "ellipsis": false,
        "clamp": 1,
        "center": true,
        "effect": "",
        "classList": [
          "ridge-bootstrap/text-success"
        ]
      },
      "propEx": {
        "text": "NumberGuess.computed.oneTimeNumber"
      },
      "events": {},
      "visible": true,
      "locked": false,
      "full": false,
      "slots": []
    },
    {
      "path": "ridge-bootstrap/typography",
      "id": "jpyntns0og",
      "style": {
        "position": "absolute",
        "visible": true,
        "x": 733,
        "y": 247,
        "width": 20,
        "height": 17.99998076065727
      },
      "styleEx": {},
      "props": {
        "text": "2",
        "color": "",
        "bgcolor": "",
        "fontSize": 24,
        "autoFontSize": false,
        "fontFamily": "",
        "ellipsis": false,
        "clamp": 1,
        "center": true,
        "effect": "",
        "classList": [
          "ridge-bootstrap/text-danger"
        ]
      },
      "propEx": {
        "text": "NumberGuess.computed.oneTimeNumber"
      },
      "events": {},
      "visible": true,
      "locked": false,
      "full": false,
      "slots": [],
      "title": "数字"
    },
    {
      "title": "absent",
      "path": "ridge-container/flex",
      "id": "uvp1x413ns",
      "style": {
        "position": "absolute",
        "visible": true,
        "x": 742,
        "y": 264,
        "width": 37,
        "height": 34
      },
      "styleEx": {},
      "props": {
        "direction": "row",
        "justify": "center",
        "alignItems": "center",
        "flexWrap": false,
        "children": [
          "jpyntns0og"
        ],
        "gap": 8,
        "padding": 8,
        "hoverable": false,
        "rectStyle": {},
        "classList": [
          "ridge-bootstrap/bg-danger-subtle",
          "ridge-bootstrap/rounded-3",
          "ridge-bootstrap/shadow-sm"
        ]
      },
      "propEx": {},
      "events": {},
      "visible": true,
      "locked": false,
      "full": false,
      "slots": []
    },
    {
      "title": "数字",
      "path": "ridge-bootstrap/typography",
      "id": "03gphfrlcn",
      "style": {
        "position": "absolute",
        "visible": true,
        "x": 733,
        "y": 247,
        "width": 20,
        "height": 17.99998076065727
      },
      "styleEx": {},
      "props": {
        "text": "2",
        "color": "",
        "bgcolor": "",
        "fontSize": 24,
        "autoFontSize": false,
        "fontFamily": "",
        "ellipsis": false,
        "clamp": 1,
        "center": true,
        "effect": "",
        "classList": [
          "ridge-bootstrap/text-warning"
        ]
      },
      "propEx": {
        "text": "NumberGuess.computed.oneTimeNumber"
      },
      "events": {},
      "visible": true,
      "locked": false,
      "full": false,
      "slots": []
    },
    {
      "title": "exists",
      "path": "ridge-container/flex",
      "id": "6ie68ja9mt",
      "style": {
        "position": "absolute",
        "visible": true,
        "x": 782,
        "y": 302,
        "width": 37,
        "height": 34
      },
      "styleEx": {},
      "props": {
        "direction": "row",
        "justify": "center",
        "alignItems": "center",
        "flexWrap": false,
        "children": [
          "03gphfrlcn"
        ],
        "gap": 8,
        "padding": 8,
        "hoverable": false,
        "rectStyle": {},
        "classList": [
          "ridge-bootstrap/bg-warning-subtle",
          "ridge-bootstrap/rounded-3",
          "ridge-bootstrap/shadow-sm"
        ]
      },
      "propEx": {},
      "events": {},
      "visible": true,
      "locked": false,
      "full": false,
      "slots": []
    },
    {
      "title": "按钮_1",
      "path": "ridge-bootstrap/button",
      "id": "bpxg6p8egw",
      "style": {
        "position": "absolute",
        "visible": true,
        "x": 0,
        "y": 0,
        "width": 100,
        "height": 62
      },
      "styleEx": {},
      "props": {
        "type": "primary",
        "src": "",
        "size": "btn-normal",
        "fontSize": 27,
        "style": "general",
        "rounded": false,
        "full": true,
        "disabled": false,
        "withBadge": false,
        "badgeCount": "",
        "text": "0"
      },
      "propEx": {},
      "events": {
        "onClick": [
          {
            "store": "NumberGuess",
            "method": "onBtnPress",
            "payload": "0"
          }
        ]
      },
      "visible": true,
      "locked": false,
      "full": false,
      "slots": []
    },
    {
      "title": "错误通知文本",
      "path": "ridge-bootstrap/typography",
      "id": "59qvsa963q",
      "style": {
        "position": "absolute",
        "visible": true,
        "x": 0,
        "y": 0,
        "width": 134,
        "height": 21
      },
      "styleEx": {},
      "props": {
        "color": "",
        "bgcolor": "",
        "fontSize": 14,
        "autoFontSize": false,
        "fontFamily": "",
        "ellipsis": true,
        "clamp": 1,
        "center": false,
        "effect": "",
        "classList": [
          "ridge-bootstrap/text-body-tertiary"
        ],
        "text": "输入错误，请重试"
      },
      "propEx": {},
      "events": {},
      "visible": true,
      "locked": false,
      "full": false,
      "slots": []
    },
    {
      "title": "弹性容器",
      "path": "ridge-container/flex",
      "id": "m5v5agjbn0",
      "style": {
        "position": "absolute",
        "visible": true,
        "x": 15,
        "y": 153,
        "width": 360,
        "height": 240
      },
      "styleEx": {},
      "props": {
        "direction": "row",
        "justify": "center",
        "alignItems": "center",
        "flexWrap": false,
        "children": [
          "mzc61e06zz"
        ],
        "gap": 0,
        "padding": 0,
        "hoverable": false,
        "rectStyle": {},
        "classList": []
      },
      "propEx": {},
      "events": {},
      "visible": true,
      "locked": false,
      "full": true,
      "slots": []
    },
    {
      "title": "切换容器_1",
      "path": "ridge-container/layers",
      "id": "tbicdg1whd",
      "style": {
        "position": "absolute",
        "visible": true,
        "x": 0,
        "y": 0,
        "width": 340,
        "height": 498
      },
      "styleEx": {},
      "props": {
        "current": "",
        "preload": true,
        "swipeable": false,
        "classList": [],
        "children": [
          "5wtdie2no4",
          "r05ipss7xq",
          "px6cc8ubva"
        ]
      },
      "propEx": {
        "current": "NumberGuess.state.statusText"
      },
      "events": {},
      "visible": true,
      "locked": false,
      "full": false,
      "slots": []
    },
    {
      "title": "弹性容器_1",
      "path": "ridge-container/flex",
      "id": "mzc61e06zz",
      "style": {
        "position": "absolute",
        "visible": true,
        "x": -2595,
        "y": 0,
        "width": 354,
        "height": 794.000020841273
      },
      "styleEx": {},
      "props": {
        "direction": "column",
        "justify": "flex-start",
        "alignItems": "center",
        "flexWrap": false,
        "children": [
          "tbicdg1whd",
          "we5srv7x4e"
        ],
        "gap": 4,
        "padding": 0,
        "hoverable": false,
        "rectStyle": {},
        "classList": []
      },
      "propEx": {},
      "events": {},
      "visible": true,
      "locked": false,
      "full": false,
      "slots": []
    },
    {
      "title": "弹性容器_2",
      "path": "ridge-container/flex",
      "id": "ahlgvi205v",
      "style": {
        "position": "absolute",
        "visible": true,
        "x": 0,
        "y": 0,
        "width": 334,
        "height": 304
      },
      "styleEx": {},
      "props": {
        "direction": "row",
        "justify": "flex-start",
        "alignItems": "flex-start",
        "flexWrap": true,
        "children": [
          "b7xkbe66u8",
          "bkojzzxq5i",
          "7tdwyxmcgc",
          "semhrj7nj1",
          "yrsaghlwyo",
          "cnuzivlho5",
          "5xwifz7wzt",
          "erdhc14knm",
          "swutric4ok",
          "ai55ywlu6o",
          "bpxg6p8egw",
          "2m7mrx44je"
        ],
        "gap": 8,
        "padding": 8,
        "hoverable": false,
        "rectStyle": {},
        "classList": []
      },
      "propEx": {},
      "events": {},
      "visible": true,
      "locked": false,
      "full": false,
      "slots": []
    },
    {
      "title": "按钮",
      "path": "ridge-bootstrap/button",
      "id": "2m7mrx44je",
      "style": {
        "position": "absolute",
        "visible": true,
        "x": 966,
        "y": 541,
        "width": 100,
        "height": 65
      },
      "styleEx": {},
      "props": {
        "type": "success",
        "src": "",
        "size": "lg",
        "fontSize": 27,
        "style": "general",
        "rounded": false,
        "full": true,
        "disabled": false,
        "withBadge": false,
        "badgeCount": "",
        "icon": "unlock"
      },
      "propEx": {},
      "events": {
        "onClick": [
          {
            "store": "NumberGuess",
            "method": "onBtnPress",
            "payload": "unlock"
          }
        ]
      },
      "visible": true,
      "locked": false,
      "full": false,
      "slots": []
    },
    {
      "title": "弹性容器_3",
      "path": "ridge-container/flex",
      "id": "zoqft0ro0s",
      "style": {
        "position": "absolute",
        "visible": true,
        "x": -628,
        "y": 0,
        "width": 193,
        "height": 88
      },
      "styleEx": {},
      "props": {
        "direction": "row",
        "justify": "center",
        "alignItems": "center",
        "flexWrap": false,
        "children": [
          "khw49z6y0a"
        ],
        "gap": 8,
        "padding": 8,
        "hoverable": false,
        "rectStyle": {},
        "classList": [
          "ridge-bootstrap/rounded-4",
          "ridge-bootstrap/bg-body-tertiary",
          "ridge-bootstrap/shadow"
        ]
      },
      "propEx": {},
      "events": {},
      "visible": true,
      "locked": false,
      "full": false,
      "slots": []
    },
    {
      "title": "弹性容器_4",
      "path": "ridge-container/flex",
      "id": "0c8dy97zod",
      "style": {
        "position": "absolute",
        "visible": true,
        "x": 0,
        "y": 0,
        "width": 312,
        "height": 51
      },
      "styleEx": {},
      "props": {
        "direction": "row",
        "justify": "flex-start",
        "alignItems": "center",
        "flexWrap": false,
        "children": [
          "hu9qr7jhs3",
          "w1ywpni0np",
          "8g6gm05k26",
          "qh4wngv3d8",
          "b936rkqmi2",
          "0p40cpyxo7"
        ],
        "gap": 8,
        "padding": 8,
        "hoverable": false,
        "rectStyle": {},
        "classList": []
      },
      "propEx": {},
      "events": {},
      "visible": true,
      "locked": false,
      "full": false,
      "slots": []
    },
    {
      "title": "文本_1",
      "path": "ridge-bootstrap/typography",
      "id": "hu9qr7jhs3",
      "style": {
        "position": "absolute",
        "visible": true,
        "x": 0,
        "y": 0,
        "width": 35,
        "height": 20
      },
      "styleEx": {},
      "props": {
        "color": "",
        "bgcolor": "",
        "fontSize": 14,
        "autoFontSize": false,
        "fontFamily": "",
        "ellipsis": true,
        "clamp": 1,
        "center": false,
        "effect": "",
        "classList": [],
        "text": "计时"
      },
      "propEx": {},
      "events": {},
      "visible": true,
      "locked": false,
      "full": false,
      "slots": []
    },
    {
      "title": "文本_2",
      "path": "ridge-bootstrap/typography",
      "id": "w1ywpni0np",
      "style": {
        "position": "absolute",
        "visible": true,
        "x": 0,
        "y": 0,
        "width": 35,
        "height": 52,
        "autoWidth": true
      },
      "styleEx": {},
      "props": {
        "text": "0",
        "color": "",
        "bgcolor": "",
        "fontSize": 32,
        "autoFontSize": false,
        "fontFamily": "",
        "ellipsis": false,
        "clamp": 1,
        "center": true,
        "effect": "",
        "classList": [
          "ridge-bootstrap/bg-body",
          "ridge-bootstrap/rounded-3",
          "ridge-bootstrap/shadow-sm",
          "ridge-bootstrap/ps-2",
          "ridge-bootstrap/pe-2"
        ]
      },
      "propEx": {
        "text": "NumberGuess.state.elapsedSeconds"
      },
      "events": {},
      "visible": true,
      "locked": false,
      "full": false,
      "slots": []
    },
    {
      "title": "文本_1",
      "path": "ridge-bootstrap/typography",
      "id": "8g6gm05k26",
      "style": {
        "position": "absolute",
        "visible": true,
        "x": 0,
        "y": 0,
        "width": 28,
        "height": 20
      },
      "styleEx": {},
      "props": {
        "color": "",
        "bgcolor": "",
        "fontSize": 14,
        "autoFontSize": false,
        "fontFamily": "",
        "ellipsis": true,
        "clamp": 1,
        "center": false,
        "effect": "",
        "classList": [],
        "text": "秒"
      },
      "propEx": {},
      "events": {},
      "visible": true,
      "locked": false,
      "full": false,
      "slots": []
    },
    {
      "title": "文本_3",
      "path": "ridge-bootstrap/typography",
      "id": "qh4wngv3d8",
      "style": {
        "position": "absolute",
        "visible": true,
        "x": 0,
        "y": 0,
        "width": 49,
        "height": 18
      },
      "styleEx": {},
      "props": {
        "text": "您还有",
        "color": "",
        "bgcolor": "",
        "fontSize": 14,
        "autoFontSize": false,
        "fontFamily": "",
        "ellipsis": true,
        "clamp": 1,
        "center": false,
        "effect": "",
        "classList": []
      },
      "propEx": {},
      "events": {},
      "visible": true,
      "locked": false,
      "full": false,
      "slots": []
    },
    {
      "title": "文本_2",
      "path": "ridge-bootstrap/typography",
      "id": "b936rkqmi2",
      "style": {
        "position": "absolute",
        "visible": true,
        "x": 0,
        "y": 0,
        "width": 35,
        "height": 52,
        "autoWidth": true
      },
      "styleEx": {},
      "props": {
        "text": "0",
        "color": "",
        "bgcolor": "",
        "fontSize": 32,
        "autoFontSize": false,
        "fontFamily": "",
        "ellipsis": false,
        "clamp": 1,
        "center": true,
        "effect": "",
        "classList": [
          "ridge-bootstrap/bg-body",
          "ridge-bootstrap/rounded-3",
          "ridge-bootstrap/shadow-sm",
          "ridge-bootstrap/ps-2",
          "ridge-bootstrap/pe-2"
        ]
      },
      "propEx": {
        "text": "NumberGuess.state.remainingAttempts"
      },
      "events": {},
      "visible": true,
      "locked": false,
      "full": false,
      "slots": []
    },
    {
      "title": "文本_3",
      "path": "ridge-bootstrap/typography",
      "id": "0p40cpyxo7",
      "style": {
        "position": "absolute",
        "visible": true,
        "x": 0,
        "y": 0,
        "width": 49,
        "height": 18
      },
      "styleEx": {},
      "props": {
        "color": "",
        "bgcolor": "",
        "fontSize": 14,
        "autoFontSize": false,
        "fontFamily": "",
        "ellipsis": true,
        "clamp": 1,
        "center": false,
        "effect": "",
        "classList": [],
        "text": "次机会"
      },
      "propEx": {},
      "events": {},
      "visible": true,
      "locked": false,
      "full": false,
      "slots": []
    },
    {
      "title": "成功",
      "path": "ridge-container/flex",
      "id": "px6cc8ubva",
      "style": {
        "position": "absolute",
        "visible": true,
        "x": 694,
        "y": 343,
        "width": 360,
        "height": 526
      },
      "styleEx": {},
      "props": {
        "direction": "column",
        "justify": "center",
        "alignItems": "center",
        "flexWrap": false,
        "children": [
          "825kcu8c2j",
          "mseqqvn03j"
        ],
        "gap": 8,
        "padding": 8,
        "hoverable": false,
        "rectStyle": {},
        "classList": []
      },
      "propEx": {},
      "events": {},
      "visible": true,
      "locked": false,
      "full": false,
      "slots": []
    },
    {
      "title": "弹性容器_6",
      "path": "ridge-container/flex",
      "id": "825kcu8c2j",
      "style": {
        "position": "absolute",
        "visible": true,
        "x": 0,
        "y": 8,
        "width": 230,
        "height": 261
      },
      "styleEx": {},
      "props": {
        "direction": "column",
        "justify": "center",
        "alignItems": "center",
        "flexWrap": false,
        "children": [
          "ntikdjwnr5",
          "n8oueq26fw",
          "j3gn9j1n1t"
        ],
        "gap": 8,
        "padding": 8,
        "hoverable": false,
        "rectStyle": {},
        "classList": []
      },
      "propEx": {},
      "events": {},
      "visible": true,
      "locked": false,
      "full": false,
      "slots": []
    },
    {
      "title": "图片",
      "path": "ridge-bootstrap/image",
      "id": "ntikdjwnr5",
      "style": {
        "position": "absolute",
        "visible": true,
        "x": 0,
        "y": 0,
        "width": 111,
        "height": 83
      },
      "styleEx": {},
      "props": {
        "fitPosition": "left",
        "src": "composite:///NotoV1GrinningFace.svg",
        "classList": []
      },
      "propEx": {},
      "events": {},
      "visible": true,
      "locked": false,
      "full": false,
      "slots": []
    },
    {
      "title": "文本_4",
      "path": "ridge-bootstrap/typography",
      "id": "n8oueq26fw",
      "style": {
        "position": "absolute",
        "visible": true,
        "x": 801,
        "y": 514,
        "width": 100,
        "height": 22
      },
      "styleEx": {},
      "props": {
        "color": "",
        "bgcolor": "",
        "fontSize": 14,
        "autoFontSize": false,
        "fontFamily": "",
        "ellipsis": false,
        "clamp": 1,
        "center": true,
        "effect": "",
        "classList": [],
        "text": "恭喜您"
      },
      "propEx": {},
      "events": {},
      "visible": true,
      "locked": false,
      "full": false,
      "slots": []
    },
    {
      "title": "文本_5",
      "path": "ridge-bootstrap/typography",
      "id": "j3gn9j1n1t",
      "style": {
        "position": "absolute",
        "visible": true,
        "x": 806,
        "y": 534,
        "width": 100,
        "height": 22
      },
      "styleEx": {},
      "props": {
        "text": "您的成绩为",
        "color": "",
        "bgcolor": "",
        "fontSize": 14,
        "autoFontSize": false,
        "fontFamily": "",
        "ellipsis": true,
        "clamp": 1,
        "center": false,
        "effect": "",
        "classList": []
      },
      "propEx": {},
      "events": {},
      "visible": true,
      "locked": false,
      "full": false,
      "slots": []
    },
    {
      "title": "按钮_2",
      "path": "ridge-bootstrap/button",
      "id": "mseqqvn03j",
      "style": {
        "position": "absolute",
        "visible": true,
        "x": -47,
        "y": -10,
        "width": 125,
        "height": 44
      },
      "styleEx": {},
      "props": {
        "text": "再玩一把",
        "type": "success",
        "src": "",
        "icon": "arrow-counterclockwise",
        "size": "lg",
        "fontSize": 16,
        "style": "outline",
        "rounded": false,
        "full": false,
        "disabled": false,
        "withBadge": false,
        "badgeCount": ""
      },
      "propEx": {},
      "events": {
        "onClick": [
          {
            "store": "NumberGuess",
            "method": "initGame",
            "payload": ""
          }
        ]
      },
      "visible": true,
      "locked": false,
      "full": false,
      "slots": []
    },
    {
      "title": "进行中",
      "path": "ridge-container/flex",
      "id": "5wtdie2no4",
      "style": {
        "position": "absolute",
        "visible": true,
        "x": 0,
        "y": 0,
        "width": 334,
        "height": 476
      },
      "styleEx": {},
      "props": {
        "direction": "column",
        "justify": "flex-start",
        "alignItems": "center",
        "flexWrap": false,
        "children": [
          "an6y3d28yq",
          "0c8dy97zod",
          "zoqft0ro0s",
          "ahlgvi205v"
        ],
        "gap": 8,
        "padding": 0,
        "hoverable": false,
        "rectStyle": {},
        "classList": []
      },
      "propEx": {},
      "events": {},
      "visible": true,
      "locked": false,
      "full": false,
      "slots": []
    },
    {
      "title": "失败",
      "path": "ridge-container/flex",
      "id": "r05ipss7xq",
      "style": {
        "position": "absolute",
        "visible": true,
        "x": 765,
        "y": 107,
        "width": 360,
        "height": 393
      },
      "styleEx": {},
      "props": {
        "direction": "column",
        "justify": "center",
        "alignItems": "center",
        "flexWrap": false,
        "children": [
          "r2snf6a0ct",
          "ip0e1igiih",
          "3pfza072ye",
          "13twvpbuuk",
          "nr0sv8inob"
        ],
        "gap": 8,
        "padding": 8,
        "hoverable": false,
        "rectStyle": {},
        "classList": []
      },
      "propEx": {},
      "events": {},
      "visible": true,
      "locked": false,
      "full": false,
      "slots": []
    },
    {
      "title": "图片_1",
      "path": "ridge-bootstrap/image",
      "id": "r2snf6a0ct",
      "style": {
        "position": "absolute",
        "visible": true,
        "x": 0,
        "y": -1049,
        "width": 90,
        "height": 130
      },
      "styleEx": {},
      "props": {
        "fitPosition": "left",
        "src": "composite:///EmojioneV1BeamingFaceWithSmilingEyes.svg",
        "classList": []
      },
      "propEx": {},
      "events": {},
      "visible": true,
      "locked": false,
      "full": false,
      "slots": []
    },
    {
      "title": "文本_6",
      "path": "ridge-bootstrap/typography",
      "id": "ip0e1igiih",
      "style": {
        "position": "absolute",
        "visible": true,
        "x": 0,
        "y": 561,
        "width": 141,
        "height": 30
      },
      "styleEx": {},
      "props": {
        "color": "",
        "bgcolor": "",
        "fontSize": 14,
        "autoFontSize": false,
        "fontFamily": "",
        "ellipsis": true,
        "clamp": 1,
        "center": false,
        "effect": "",
        "classList": [],
        "text": "猜错了，正确数字为"
      },
      "propEx": {},
      "events": {},
      "visible": true,
      "locked": false,
      "full": false,
      "slots": []
    },
    {
      "title": "文本_7",
      "path": "ridge-bootstrap/typography",
      "id": "3pfza072ye",
      "style": {
        "position": "absolute",
        "visible": true,
        "x": -372,
        "y": 0,
        "width": 105,
        "height": 52
      },
      "styleEx": {},
      "props": {
        "text": "1234",
        "color": "",
        "bgcolor": "",
        "fontSize": 32,
        "autoFontSize": false,
        "fontFamily": "",
        "ellipsis": false,
        "clamp": 1,
        "center": true,
        "effect": "",
        "classList": [
          "ridge-bootstrap/bg-body",
          "ridge-bootstrap/shadow",
          "ridge-bootstrap/rounded-4",
          "ridge-bootstrap/text-success"
        ]
      },
      "propEx": {
        "text": "NumberGuess.state.secret"
      },
      "events": {},
      "visible": true,
      "locked": false,
      "full": false,
      "slots": []
    },
    {
      "title": "按钮_2",
      "path": "ridge-bootstrap/button",
      "id": "nr0sv8inob",
      "style": {
        "position": "absolute",
        "visible": true,
        "x": -47,
        "y": -10,
        "width": 125,
        "height": 44
      },
      "styleEx": {},
      "props": {
        "text": "再玩一把",
        "type": "success",
        "src": "",
        "icon": "arrow-counterclockwise",
        "size": "lg",
        "fontSize": 16,
        "style": "outline",
        "rounded": false,
        "full": false,
        "disabled": false,
        "withBadge": false,
        "badgeCount": ""
      },
      "propEx": {},
      "events": {
        "onClick": [
          {
            "store": "NumberGuess",
            "method": "initGame",
            "payload": ""
          }
        ]
      },
      "visible": true,
      "locked": false,
      "full": false,
      "slots": []
    },
    {
      "title": "文本_8",
      "path": "ridge-bootstrap/typography",
      "id": "an6y3d28yq",
      "style": {
        "position": "absolute",
        "visible": true,
        "x": 0,
        "y": 0,
        "width": 291,
        "height": 20
      },
      "styleEx": {},
      "props": {
        "text": "猜出由 0 - 9 组成的无重复四位密码。",
        "color": "",
        "bgcolor": "",
        "fontSize": 14,
        "autoFontSize": false,
        "fontFamily": "",
        "ellipsis": true,
        "clamp": 1,
        "center": false,
        "effect": "",
        "classList": []
      },
      "propEx": {},
      "events": {},
      "visible": true,
      "locked": false,
      "full": false,
      "slots": []
    },
    {
      "title": "弹性容器_5",
      "path": "ridge-container/flex",
      "id": "13twvpbuuk",
      "style": {
        "position": "absolute",
        "visible": true,
        "x": 0,
        "y": -4720,
        "width": 324,
        "height": 38
      },
      "styleEx": {},
      "props": {
        "direction": "row",
        "justify": "flex-start",
        "alignItems": "flex-start",
        "flexWrap": false,
        "children": [],
        "gap": 8,
        "padding": 8,
        "hoverable": false,
        "rectStyle": {},
        "classList": []
      },
      "propEx": {},
      "events": {},
      "visible": true,
      "locked": false,
      "full": false,
      "slots": []
    }
  ],
  "name": "index",
  "children": [
    "m5v5agjbn0"
  ]
}