{
  "version": "1.2.0",
  "style": {
    "height": 440,
    "background": "",
    "classNames": [],
    "width": 559
  },
  "properties": {},
  "cssFiles": [],
  "jsFiles": [
    "composite:///js/avatar.js"
  ],
  "elements": [
    {
      "title": "上传",
      "path": "ridge-semi/upload",
      "id": "7sd9rhtk3g",
      "style": {
        "position": "absolute",
        "visible": true,
        "x": 10,
        "y": 9,
        "width": 109,
        "height": 31
      },
      "styleEx": {},
      "props": {
        "value": [],
        "type": "button",
        "icon": "IconCloudUploadStroked",
        "url": "",
        "btnText": "点击上传",
        "fileLimit": "",
        "maxSize": 10,
        "multiple": false,
        "directory": false
      },
      "propEx": {
        "url": null,
        "value": "Avatar.state.upload"
      },
      "events": {},
      "visible": true,
      "locked": false,
      "full": false,
      "$id": "https://ridge-ui.com/schemas/element",
      "slots": []
    },
    {
      "title": "截图",
      "path": "ridge-cropperjs/cropper",
      "id": "398cjnqw33",
      "style": {
        "position": "absolute",
        "visible": true,
        "x": 10,
        "y": 48,
        "width": 360,
        "height": 360
      },
      "styleEx": {},
      "props": {
        "src": "",
        "aspectRatio": 1,
        "outputWidth": 160,
        "outputHeight": 160
      },
      "propEx": {
        "src": "Avatar.state.upload"
      },
      "events": {
        "blobChange": [
          {
            "store": "Avatar",
            "method": "setCroppedDataUrl",
            "payload": ""
          }
        ]
      },
      "visible": true,
      "locked": false,
      "full": false,
      "$id": "https://ridge-ui.com/schemas/element",
      "slots": []
    },
    {
      "title": "图片",
      "path": "ridge-semi/image",
      "id": "sx0prrvncj",
      "style": {
        "position": "absolute",
        "visible": true,
        "x": 397,
        "y": 86,
        "width": 128,
        "height": 128
      },
      "styleEx": {},
      "props": {
        "src": "",
        "preview": true
      },
      "propEx": {
        "src": "Avatar.state.croppedDataUrl"
      },
      "events": {},
      "visible": true,
      "locked": false,
      "full": false,
      "$id": "https://ridge-ui.com/schemas/element",
      "slots": []
    },
    {
      "title": "文本",
      "path": "ridge-semi/text",
      "id": "yr40mycfxq",
      "style": {
        "position": "absolute",
        "visible": true,
        "x": 397,
        "y": 48,
        "width": 71,
        "height": 23
      },
      "styleEx": {},
      "props": {
        "size": "normal",
        "copyable": false,
        "ellipsis": false,
        "type": "primary",
        "link": "",
        "classList": [],
        "text": "头像预览"
      },
      "propEx": {},
      "events": {},
      "visible": true,
      "locked": false,
      "full": false,
      "$id": "https://ridge-ui.com/schemas/element",
      "slots": []
    },
    {
      "title": "头像",
      "path": "ridge-semi/avatar",
      "id": "o1zr649h7h",
      "style": {
        "position": "absolute",
        "visible": true,
        "x": 397,
        "y": 245,
        "width": 128,
        "height": 128
      },
      "styleEx": {},
      "props": {
        "shape": "circle",
        "src": "",
        "text": "A",
        "color": "blue",
        "borderColor": "blue",
        "contentMotion": false,
        "topLabel": "",
        "bottomPlus": false,
        "size": "extra-large"
      },
      "propEx": {
        "src": "Avatar.state.croppedDataUrl"
      },
      "events": {},
      "visible": true,
      "locked": false,
      "full": false,
      "$id": "https://ridge-ui.com/schemas/element",
      "slots": []
    },
    {
      "title": "按钮",
      "path": "ridge-semi/button",
      "id": "7xowsdtjax",
      "style": {
        "position": "absolute",
        "visible": true,
        "x": 461,
        "y": 8,
        "width": 77,
        "height": 32
      },
      "styleEx": {},
      "props": {
        "icon": "IconCheckCircleStroked",
        "size": "default",
        "theme": "solid",
        "disabled": false,
        "iconSize": 18,
        "loading": false,
        "type": "primary",
        "text": "完成"
      },
      "propEx": {
        "disabled": "Avatar.computed.confirmDisabled"
      },
      "events": {
        "onClick": [
          {
            "store": "Avatar",
            "method": "saveUserAvatar",
            "payload": ""
          }
        ]
      },
      "visible": true,
      "locked": false,
      "full": false,
      "$id": "https://ridge-ui.com/schemas/element",
      "slots": []
    }
  ],
  "name": "AvatarEdit",
  "children": [
    "7sd9rhtk3g",
    "398cjnqw33",
    "sx0prrvncj",
    "yr40mycfxq",
    "o1zr649h7h",
    "7xowsdtjax"
  ]
}